Metadata-Version: 2.4
Name: tipp3
Version: 0.3
Summary: TIPP3 - A Phylogeney-Based Abundance Profiling Tool
Author-email: Chengze Shen <chengze5@illinois.edu>
License:                     GNU GENERAL PUBLIC LICENSE
Project-URL: Homepage, https://github.com/c5shen/TIPP3
Project-URL: Changelog, https://github.com/c5shen/TIPP3/blob/main/CHANGELOG.rst
Classifier: Development Status :: 4 - Beta
Classifier: Operating System :: OS Independent
Classifier: Intended Audience :: Developers
Classifier: Intended Audience :: Science/Research
Classifier: Topic :: Scientific/Engineering :: Bio-Informatics
Classifier: Topic :: Software Development
Classifier: License :: OSI Approved :: GNU General Public License (GPL)
Classifier: Programming Language :: Python
Classifier: Programming Language :: Python :: 3
Classifier: Programming Language :: Python :: 3.7
Classifier: Programming Language :: Python :: 3.8
Classifier: Programming Language :: Python :: 3.9
Classifier: Programming Language :: Python :: 3.10
Classifier: Programming Language :: Python :: 3.11
Classifier: Programming Language :: Python :: 3.12
Requires-Python: >=3.7
License-File: LICENSE
Requires-Dist: configparser>=5.0.0
Requires-Dist: DendroPy>=4.5.2
Requires-Dist: numpy>=1.21.6
Requires-Dist: psutil>=5.0.0
Requires-Dist: setuptools>=60.0.0
Requires-Dist: treeswift>=1.1.28
Requires-Dist: witch-msa>=1.0.7
Requires-Dist: bscampp>=1.0.7
Dynamic: license-file
